conaction/__init__.py
conaction/estimators.py
conaction/numparam.py
conaction/sampling.py
conaction/symparam.py
conaction-0.0.44.dist-info/LICENSE
conaction-0.0.44.dist-info/METADATA
conaction-0.0.44.dist-info/WHEEL
conaction-0.0.44.dist-info/top_level.txt
conaction-0.0.44.dist-info/RECORD
