Metadata-Version: 2.1
Name: conaction
Version: 0.0.44
Summary: Efficient implmenetations of instantiations of the Trinity of Covariation.
Home-page: https://github.com/galenseilis/ConAction
Author: Galen Seilis
Author-email: seilis@unbc.ca
Project-URL: Bug Tracker, https://github.com/galenseilis/ConAction/issues
Classifier: Programming Language :: Python :: 3
Classifier: License :: OSI Approved :: BSD License
Classifier: Operating System :: OS Independent
Requires-Python: >=3.6
License-File: LICENSE
Requires-Dist: networkx
Requires-Dist: numpy
Requires-Dist: tqdm
Requires-Dist: pathos
Requires-Dist: scipy
Requires-Dist: sympy
